lilpipe/__init__.py
lilpipe/engine.py
lilpipe/enums.py
lilpipe/models.py
lilpipe/step.py
lilpipe/utils.py
lilpipe-0.1.6.dist-info/LICENSE
lilpipe-0.1.6.dist-info/METADATA
lilpipe-0.1.6.dist-info/WHEEL
lilpipe-0.1.6.dist-info/RECORD
