Metadata-Version: 2.3
Name: lilpipe
Version: 0.1.6
Summary: A tiny, typed, sequential pipeline engine for Python
License: Apache License
Author: Andrew Ruba
Requires-Python: >=3.11
Classifier: License :: OSI Approved :: Apache Software License
Classifier: Programming Language :: Python :: 3
Classifier: Programming Language :: Python :: 3.11
Classifier: Programming Language :: Python :: 3.12
Classifier: Programming Language :: Python :: 3.13
Classifier: Typing :: Typed
Requires-Dist: pydantic (>=2.11.7,<3.0.0)
